odoo9_addon_scheduler_error_mailer-9.0.1.0.0.99.dev8-py2.7-nspkg.pth
odoo9_addon_scheduler_error_mailer-9.0.1.0.0.99.dev8.dist-info/DESCRIPTION.rst
odoo9_addon_scheduler_error_mailer-9.0.1.0.0.99.dev8.dist-info/METADATA
odoo9_addon_scheduler_error_mailer-9.0.1.0.0.99.dev8.dist-info/RECORD
odoo9_addon_scheduler_error_mailer-9.0.1.0.0.99.dev8.dist-info/WHEEL
odoo9_addon_scheduler_error_mailer-9.0.1.0.0.99.dev8.dist-info/metadata.json
odoo9_addon_scheduler_error_mailer-9.0.1.0.0.99.dev8.dist-info/namespace_packages.txt
odoo9_addon_scheduler_error_mailer-9.0.1.0.0.99.dev8.dist-info/top_level.txt
odoo_addons/scheduler_error_mailer/README.rst
odoo_addons/scheduler_error_mailer/__init__.py
odoo_addons/scheduler_error_mailer/__openerp__.py
odoo_addons/scheduler_error_mailer/data/ir_cron_email_tpl.xml
odoo_addons/scheduler_error_mailer/demo/ir_cron_demo.xml
odoo_addons/scheduler_error_mailer/i18n/ca.po
odoo_addons/scheduler_error_mailer/i18n/de.po
odoo_addons/scheduler_error_mailer/i18n/pt_BR.po
odoo_addons/scheduler_error_mailer/i18n/scheduler_error_mailer.pot
odoo_addons/scheduler_error_mailer/i18n/sl.po
odoo_addons/scheduler_error_mailer/i18n/zh_CN.po
odoo_addons/scheduler_error_mailer/images/scheduler_error_mailer.jpg
odoo_addons/scheduler_error_mailer/models/__init__.py
odoo_addons/scheduler_error_mailer/models/ir_cron.py
odoo_addons/scheduler_error_mailer/static/description/icon.png
odoo_addons/scheduler_error_mailer/views/ir_cron.xml
